robotjes/__init__.py
robotjes/bot/__init__.py
robotjes/bot/robo.py
robotjes/bot/robo_shell.py
robotjes/bot/robo_thread.py
robotjes/client/__init__.py
robotjes/client/engine_handler.py
robotjes/client/player.py
robotjes/client/rest_client.py
robotjes/client/viewer.py
robotjes/client/aui/__init__.py
robotjes/client/aui/player_screen.py
robotjes/client/aui/viewer_screen.py
robotjes/local/__init__.py
robotjes/local/requestor.py
robotjes/sim/__init__.py
robotjes/sim/engine.py
robotjes/sim/map.py
robotjes/sim/mazes.py
robotjes/sim/recording.py
robotjes/sim/world.py
robotjes/sim/success/__init__.py
robotjes/sim/success/language.py
robotjes/sim/success/semantics.py
robotjes/sim/success/success.py
robotjes_client-0.0.1a6.data/scripts/ascii_local_player
robotjes_client-0.0.1a6.data/scripts/ascii_remote_player
robotjes_client-0.0.1a6.data/scripts/cli_local_player
robotjes_client-0.0.1a6.data/scripts/cli_remote_player
robotjes_client-0.0.1a6.dist-info/METADATA
robotjes_client-0.0.1a6.dist-info/WHEEL
robotjes_client-0.0.1a6.dist-info/top_level.txt
robotjes_client-0.0.1a6.dist-info/RECORD
