Metadata-Version: 2.1
Name: robotjes-client
Version: 0.0.1a6
Summary: Client package for the Robomind Academy Python course
Home-page: https://github.com/Janvanoorschot/robotjes-client
Author: Jan van Oorschot
Author-email: info@robomindacademy.com
License: UNKNOWN
Project-URL: Bug Reports, https://github.com/Janvanoorschot/robotjes-client/issues
Project-URL: Source, https://github.com/Janvanoorschot/robotjes-client/
Keywords: educational,learning,student,programming
Platform: UNKNOWN
Classifier: Development Status :: 3 - Alpha
Classifier: Intended Audience :: Education
Classifier: Topic :: Education
Classifier: License :: OSI Approved :: GNU General Public License v3 (GPLv3)
Classifier: Programming Language :: Python :: 3.8
Requires-Python: >=3.6, <4
Requires-Dist: asciimatics
Requires-Dist: requests
Requires-Dist: pyparsing
